magpy/__init__.py
magpy/__main__.py
magpy/app.py
magpy/cli.py
magpy/main_window.py
magpy/controllers/__init__.py
magpy/controllers/audio_controller.py
magpy/core/__init__.py
magpy/core/audio.py
magpy/core/measurements.py
magpy/core/selection.py
magpy/core/spectrogram.py
magpy/screens/__init__.py
magpy/screens/base.py
magpy/screens/batch_screen.py
magpy/screens/pipeline_screen.py
magpy/screens/terminal.py
magpy/screens/training_screen.py
magpy/widgets/__init__.py
magpy/widgets/detection_dialog.py
magpy/widgets/detection_results.py
magpy/widgets/navigation_bar.py
magpy/widgets/playback.py
magpy/widgets/properties_panel.py
magpy/widgets/selection_table.py
magpy/widgets/spectrogram.py
magpy/widgets/waveform.py
magpy/widgets/node_graph/__init__.py
magpy/widgets/node_graph/connection.py
magpy/widgets/node_graph/graph_widget.py
magpy/widgets/node_graph/node.py
magpy/widgets/node_graph/node_palette.py
magpy/widgets/node_graph/parameter_panel.py
magpy/workers/__init__.py
magpy/workers/detection_worker.py
magpy_gui-0.1.4.dist-info/METADATA
magpy_gui-0.1.4.dist-info/WHEEL
magpy_gui-0.1.4.dist-info/entry_points.txt
magpy_gui-0.1.4.dist-info/licenses/LICENSE
magpy_gui-0.1.4.dist-info/RECORD
